metabolize/__init__.py
metabolize/_convert.py
metabolize/_converters.py
metabolize/_datetime_converters.py
metabolize/_defs.py
metabolize/_enumcache.py
metabolize/_generic_converters.py
metabolize/_special_converters.py
metabolize/py.typed
metabolize-0.1.dist-info/LICENSE
metabolize-0.1.dist-info/METADATA
metabolize-0.1.dist-info/WHEEL
metabolize-0.1.dist-info/top_level.txt
metabolize-0.1.dist-info/RECORD
