Metadata-Version: 2.1
Name: metabolize
Version: 0.1
Summary: A small example package
Author-email: Julian Bertram <tirednesscankill@warhog.net>
Project-URL: Homepage, https://github.com/scravy/metabolize
Project-URL: Issues, https://github.com/scravy/metabolize/issues
Classifier: Programming Language :: Python :: 3
Classifier: License :: OSI Approved :: MIT License
Classifier: Operating System :: OS Independent
Classifier: Development Status :: 3 - Alpha
Classifier: Intended Audience :: Developers
Classifier: Topic :: Software Development :: Libraries
Classifier: Typing :: Typed
Requires-Python: >=3.11
License-File: LICENSE
Requires-Dist: frzn<2,>=1.0.1
Provides-Extra: dev
Requires-Dist: black==24.10.0; extra == "dev"
Requires-Dist: build==1.2.1; extra == "dev"
Requires-Dist: flake8==7.1.1; extra == "dev"
Requires-Dist: mypy==1.11.2; extra == "dev"
Requires-Dist: pylint==3.3.0; extra == "dev"
Requires-Dist: pytest==8.3.3; extra == "dev"
Requires-Dist: pytest-asyncio==0.24.0; extra == "dev"
Requires-Dist: pytest-random-order==1.1.1; extra == "dev"
Requires-Dist: twine==5.1.1; extra == "dev"
Requires-Dist: wheel==0.44.0; extra == "dev"
